rprint/__init__.py
rprint/rprint.py
rprint-0.0.8.dist-info/DESCRIPTION.rst
rprint-0.0.8.dist-info/METADATA
rprint-0.0.8.dist-info/RECORD
rprint-0.0.8.dist-info/WHEEL
rprint-0.0.8.dist-info/metadata.json
rprint-0.0.8.dist-info/top_level.txt
